baci/__init__.py
baci/actions.py
baci/formatters.py
baci/baci/__init__.py
baci/baci/baci.py
baci/factories/__init__.py
baci/factories/_argument.py
baci/factories/command.py
baci/models/__init__.py
baci/models/_command.py
baci/models/arg.py
baci/models/flag.py
baci/repositories/__init__.py
baci/repositories/make_command.py
baci/util/__init__.py
baci-0.0.1.dist-info/LICENSE
baci-0.0.1.dist-info/METADATA
baci-0.0.1.dist-info/WHEEL
baci-0.0.1.dist-info/top_level.txt
baci-0.0.1.dist-info/RECORD
