Metadata-Version: 2.1
Name: baci
Version: 0.0.1
Summary: Bolt A Cli Interface (onto your python functions)
Author-email: Nick Palenchar <nickpal@nickpalenchar.com>
Project-URL: Homepage, https://github.com/nickpalenchar/baci
Project-URL: Issues, https://github.com/nickpalenchar/baci/issues
Classifier: Programming Language :: Python :: 3
Classifier: License :: OSI Approved :: MIT License
Classifier: Operating System :: OS Independent
Classifier: Development Status :: 1 - Planning
Requires-Python: >=3.10
License-File: LICENSE
